TansuoEs6WeiWan/README.md
TansuoEs6WeiWan/__init__.py
TansuoEs6WeiWan/__main__.py
TansuoEs6WeiWan/file.epub
TansuoEs6WeiWan/index.html
TansuoEs6WeiWan/css/__init__.py
TansuoEs6WeiWan/css/annotations.css
TansuoEs6WeiWan/css/main.css
TansuoEs6WeiWan/css/normalize.css
TansuoEs6WeiWan/css/popup.css
TansuoEs6WeiWan/font/__init__.py
TansuoEs6WeiWan/font/fontello.eot
TansuoEs6WeiWan/font/fontello.svg
TansuoEs6WeiWan/font/fontello.ttf
TansuoEs6WeiWan/font/fontello.woff
TansuoEs6WeiWan/img/__init__.py
TansuoEs6WeiWan/img/annotator-glyph-sprite.png
TansuoEs6WeiWan/img/annotator-icon-sprite.png
TansuoEs6WeiWan/img/apple-touch-icon.png
TansuoEs6WeiWan/img/cancelfullscreen.png
TansuoEs6WeiWan/img/close.png
TansuoEs6WeiWan/img/fullscreen.png
TansuoEs6WeiWan/img/loader.gif
TansuoEs6WeiWan/img/menu-icon.png
TansuoEs6WeiWan/img/save.png
TansuoEs6WeiWan/img/saved.png
TansuoEs6WeiWan/img/settings-s.png
TansuoEs6WeiWan/img/settings.png
TansuoEs6WeiWan/img/star.png
TansuoEs6WeiWan/js/__init__.py
TansuoEs6WeiWan/js/epub.js
TansuoEs6WeiWan/js/epub.min.js
TansuoEs6WeiWan/js/epub.min.map
TansuoEs6WeiWan/js/hooks.min.js
TansuoEs6WeiWan/js/hooks.min.map
TansuoEs6WeiWan/js/reader.js
TansuoEs6WeiWan/js/reader.js.map
TansuoEs6WeiWan/js/reader.min.js
TansuoEs6WeiWan/js/reader.min.map
TansuoEs6WeiWan/js/hooks/__init__.py
TansuoEs6WeiWan/js/hooks/extensions/__init__.py
TansuoEs6WeiWan/js/hooks/extensions/highlight.js
TansuoEs6WeiWan/js/libs/__init__.py
TansuoEs6WeiWan/js/libs/jquery.min.js
TansuoEs6WeiWan/js/libs/localforage.min.js
TansuoEs6WeiWan/js/libs/screenfull.js
TansuoEs6WeiWan/js/libs/screenfull.min.js
TansuoEs6WeiWan/js/libs/zip.min.js
TansuoEs6WeiWan/js/plugins/__init__.py
TansuoEs6WeiWan/js/plugins/hypothesis.js
TansuoEs6WeiWan/js/plugins/search.js
tansuo_es6_wei_wan-2024.3.2.0.dist-info/METADATA
tansuo_es6_wei_wan-2024.3.2.0.dist-info/WHEEL
tansuo_es6_wei_wan-2024.3.2.0.dist-info/entry_points.txt
tansuo_es6_wei_wan-2024.3.2.0.dist-info/top_level.txt
tansuo_es6_wei_wan-2024.3.2.0.dist-info/RECORD
